{
  "users": [
    {
      "id": 1,
      "name": "Ali"
    },
    {
      "id": "fbc4",
      "name": "Felicia Corwin"
    },
    {
      "id": "8cc4",
      "name": "Dean Stehr"
    },
    {
      "id": "61a3",
      "name": "Rosalie Vandervort"
    }
  ],
  "albums": [
    {
      "id": 10,
      "title": "hikingtrip",
      "userId": null
    },
    {
      "id": "98b1",
      "userId": null,
      "title": "Refined Wooden Chair"
    },
    {
      "id": "2aec",
      "userId": null,
      "title": "Unbranded Fresh Tuna"
    },
    {
      "id": "984a",
      "userId": null,
      "title": "Awesome Concrete Salad"
    },
    {
      "id": "a4f3",
      "userId": null,
      "title": "Electronic Concrete Computer"
    },
    {
      "id": "f407",
      "userId": null,
      "title": "Oriental Steel Keyboard"
    },
    {
      "id": "d1dd",
      "userId": null,
      "title": "Unbranded Cotton Pizza"
    },
    {
      "id": "9d93",
      "userId": null,
      "title": "Fantastic Granite Bike"
    },
    {
      "id": "959a",
      "userId": null,
      "title": "Oriental Cotton Bike"
    },
    {
      "id": "1a7b",
      "userId": null,
      "title": "Modern Concrete Keyboard"
    },
    {
      "id": "c535",
      "userId": null,
      "title": "Bespoke Plastic Car"
    },
    {
      "id": "b1a2",
      "userId": null,
      "title": "Sleek Concrete Chips"
    },
    {
      "id": "7385",
      "userId": null,
      "title": "Fantastic Plastic Bacon"
    },
    {
      "id": "85bc",
      "userId": null,
      "title": "Sleek Bronze Keyboard"
    },
    {
      "id": "967d",
      "userId": null,
      "title": "Rustic Rubber Chicken"
    },
    {
      "id": "a508",
      "userId": 1,
      "title": "Small Concrete Salad"
    },
    {
      "id": "1134",
      "userId": 1,
      "title": "Refined Steel Cheese"
    },
    {
      "id": "30f1",
      "userId": "fbc4",
      "title": "Modern Rubber Shirt"
    },
    {
      "id": "bf6b",
      "userId": "8cc4",
      "title": "Rustic Cotton Soap"
    },
    {
      "id": "acf6",
      "userId": "8cc4",
      "title": "Elegant Rubber Salad"
    }
  ],
  "photos": []
}